opendiamond/scope/__init__.py
opendiamond/scope/cli.py
opendiamond/scope/cli_generate.py
opendiamond/scope/cli_import.py
opendiamond/scope/cli_options.py
opendiamond/scope/cli_verify.py
opendiamond_scope-10.2.1.dist-info/entry_points.txt
opendiamond_scope-10.2.1.dist-info/LICENSES/MIT.txt
opendiamond_scope-10.2.1.dist-info/LICENSES/CC0-1.0.txt
opendiamond_scope-10.2.1.dist-info/LICENSES/EPL-1.0.txt
opendiamond_scope-10.2.1.dist-info/WHEEL
opendiamond_scope-10.2.1.dist-info/METADATA
opendiamond_scope-10.2.1.dist-info/RECORD
