Metadata-Version: 2.1
Name: opendiamond-scope
Version: 10.2.1
Summary: OpenDiamond scope manipulation library and tools
Home-page: https://diamond.cs.cmu.edu
License: EPL-1.0
Author: Carnegie Mellon University
Author-email: diamond@cs.cmu.edu
Requires-Python: >=3.6.1,<4.0
Classifier: License :: OSI Approved :: Eclipse Public License 1.0 (EPL-1.0)
Classifier: Programming Language :: Python :: 3
Classifier: Programming Language :: Python :: 3.10
Classifier: Programming Language :: Python :: 3.7
Classifier: Programming Language :: Python :: 3.8
Classifier: Programming Language :: Python :: 3.9
Requires-Dist: click (>=8.0.3,<9.0.0)
Requires-Dist: cryptography (>=35.0.0,<36.0.0)
Requires-Dist: importlib-metadata (>=4.8.1,<5.0.0); python_version < "3.8"
Requires-Dist: python-dateutil (>=1.5)
Project-URL: Repository, https://github.com/cmusatyalab/opendiamond-scope
